ml_backtest/__init__.py
ml_backtest/backtest/__init__.py
ml_backtest/backtest/backtest.py
ml_backtest/data/__init__.py
ml_backtest/data/data.py
ml_backtest/interfaces/__init__.py
ml_backtest/interfaces/interface.py
ml_backtest/machine_learning/__init__.py
ml_backtest/machine_learning/data.py
ml_backtest/machine_learning/wrapper.py
ml_backtest/models/__init__.py
ml_backtest/models/rfr.py
ml_backtest/strategies/__init__.py
ml_backtest/strategies/bullishengulfing.py
ml_backtest/strategies/bullishharami.py
ml_backtest/strategies/dragonflydoji.py
ml_backtest/strategies/hammer.py
ml_backtest/strategies/invertedhammer.py
ml_backtest/strategies/morningstar.py
ml_backtest/strategies/morningstardoji.py
ml_backtest/strategies/piercingpattern.py
tests/__init__.py
tests/test_ml_backtest.py
ml_backtest-0.1.3.dist-info/LICENSE
ml_backtest-0.1.3.dist-info/METADATA
ml_backtest-0.1.3.dist-info/WHEEL
ml_backtest-0.1.3.dist-info/top_level.txt
ml_backtest-0.1.3.dist-info/RECORD
