Metadata-Version: 2.1
Name: ml_backtest
Version: 0.1.3
Summary: Backtesting of trading strategies with machine learning.
Home-page: https://github.com/MaxwellMendenhall/ml-backtest
Author: Maxwell Mendenhall
Author-email: mendenhallmaxwell@gmail.com
License: MIT
Classifier: Development Status :: 3 - Alpha
Classifier: Intended Audience :: Developers
Classifier: Topic :: Software Development :: Libraries :: Python Modules
Classifier: License :: OSI Approved :: MIT License
Classifier: Programming Language :: Python :: 3
Classifier: Programming Language :: Python :: 3.11
Requires-Python: >=3.11
License-File: LICENSE
Requires-Dist: pandas ~=2.2.1
Requires-Dist: scikit-learn ~=1.3.2
Requires-Dist: numpy ~=1.26.4
Requires-Dist: tqdm ~=4.66.2
Requires-Dist: joblib ~=1.3.2
Requires-Dist: TA-Lib ~=0.4.0
